ffexport/__init__.py
ffexport/__main__.py
ffexport/common.py
ffexport/demo.py
ffexport/log.py
ffexport/merge_db.py
ffexport/model.py
ffexport/parse_db.py
ffexport/py.typed
ffexport/save_hist.py
ffexport/serialize.py
ffexport-0.1.10.dist-info/LICENSE
ffexport-0.1.10.dist-info/METADATA
ffexport-0.1.10.dist-info/WHEEL
ffexport-0.1.10.dist-info/entry_points.txt
ffexport-0.1.10.dist-info/top_level.txt
ffexport-0.1.10.dist-info/RECORD
