Metadata-Version: 2.1
Name: ffexport
Version: 0.1.10
Summary: export/interface with firefox history/site metadata
Home-page: https://github.com/seanbreckenridge/ffexport
Author: Sean Breckenridge
Author-email: seanbrecke@gmail.com
License: MIT
Keywords: firefox history backup data
Platform: UNKNOWN
Classifier: License :: OSI Approved :: MIT License
Classifier: Programming Language :: Python
Classifier: Programming Language :: Python :: 3
Classifier: Programming Language :: Python :: 3.6
Classifier: Programming Language :: Python :: 3.7
Classifier: Programming Language :: Python :: 3.8
Classifier: Programming Language :: Python :: 3.9
Requires-Dist: click
Requires-Dist: logzero
Requires-Dist: IPython
Provides-Extra: testing
Requires-Dist: pytest ; extra == 'testing'
Requires-Dist: mypy ; extra == 'testing'
